[{"run_id": 9223370392799849607, "name": "run from keep", "distance": 3036.5553623861842, "moving_time": "0:22:26", "type": "Run", "start_date": "2022-02-05 09:33:00", "start_date_local": "2022-02-05 17:33:00", "location_country": "{'latitude': 40.08512252184916, 'longitude': 116.23510900052487, 'country': '\u4e2d\u56fd', 'nationCode': '156', 'province': '\u5317\u4eac\u5e02', 'city': '\u5317\u4eac\u5e02', 'cityCode': '010', 'district': '\u6d77\u6dc0\u533a', 'districtCode': '110108'}", "summary_polyline": "_btsFqtldU??????Gd@Ur@vArDFNNl@DNBLN@VQJG@E?c@Ou@GOCQM]GKK_@EMCMEOKa@ESEOOkACWWuADy@A?NEPCf@Ot@W^MJILGZSf@SJEJIVMNETMl@WNILG^QLENK\\QDUQe@GQIe@Bg@^UDk@Sc@OKO_@GQC_@Pw@KeAGUMg@CQGUs@]SbAVj@JTd@~@JjA@XDt@Rf@\\X|@dADVNdADVDRFj@Fn@El@EXFdADPHRZz@Bl@ARCN@~@FPBVp@j@XLTd@Dj@D\\Jp@FVTxAFb@?JATDN@F@FFPAbA?PAS?WIaAEQMg@CSGi@AWAUIe@ESEUKi@CWOe@g@Wm@s@COIq@@WBs@UsAIQGQMaAD_@Hi@@QCi@GSESUe@s@H]XQFm@d@OHMH_@Py@Va@VOLc@Fm@VOF_@Vy@J?EGMEEIMCKAIAGCKAIAICIEQAGCIESIQAKCGAGCGAGESCM", "average_heartrate": null, "average_speed": 2.2559846674488737, "streak": 1}]